{
  "schemaVersion": 1,
  "id": "iseeyou",
  "version": "${version}",
  "name": "ISeeYou",
  "description": "一个玩家行为录制和回放的Fabric服务器MOD",
  "authors": [
    "xor7"
  ],
  "contact": {
    "homepage": "https://github.com/xor7/ISeeYou",
    "sources": "https://github.com/xor7/ISeeYou"
  },
  "license": "GPL-3.0",
  "icon": "assets/iseeyou/icon.png",
  "environment": "server",
  "entrypoints": {
    "main": [
      "cn.xor7.iseeyou.ISeeYouClient"
    ]
  },
  "mixins": [
    "iseeyou.mixins.json"
  ],
  "depends": {
    "fabricloader": ">=${loader_version}",
    "fabric-api": "*",
    "minecraft": "~${minecraft_version}",
    "java": ">=21"
  }
} 